quicklearning/classification/image/__init__.py
quicklearning/classification/image/automodel.py
quicklearning/classification/image/callbacks.py
quicklearning/classification/image/colab.py
quicklearning/classification/image/custom.py
quicklearning/classification/image/lite.py
quicklearning/classification/image/model.py
quicklearning/classification/image/quick.py
quicklearning-0.0.39.dist-info/LICENSE.txt
quicklearning-0.0.39.dist-info/METADATA
quicklearning-0.0.39.dist-info/WHEEL
quicklearning-0.0.39.dist-info/top_level.txt
quicklearning-0.0.39.dist-info/RECORD
