Metadata-Version: 2.1
Name: quicklearning
Version: 0.0.39
Summary: Create Tensorflow models and train them fast and easy
Home-page: https://github.com/JorgePoblete/quicklearning
Author: koke
Author-email: jpobleteriquelme@gmail.com
License: MIT
Platform: UNKNOWN
Classifier: Programming Language :: Python :: 3
Classifier: License :: OSI Approved :: MIT License
Classifier: Operating System :: OS Independent
Requires-Python: >=3.6
Requires-Dist: requests (~=2.24.0)
Requires-Dist: joblib (~=0.16.0)
Requires-Dist: tqdm (~=4.49.0)
Requires-Dist: matplotlib (~=3.3.2)
Requires-Dist: Pillow (~=7.2.0)
Requires-Dist: DuckDuckGoImages (~=2.0.0)
Requires-Dist: tensorflow (~=2.3.1)
Requires-Dist: tensorflow-hub (~=0.10.0)
Provides-Extra: dev
Requires-Dist: pytest (>=3.7) ; extra == 'dev'
